SemiBin/atomicwrite.py
SemiBin/citation.py
SemiBin/cluster.py
SemiBin/fasta.py
SemiBin/generate_coverage.py
SemiBin/generate_kmer.py
SemiBin/gtdb.py
SemiBin/long_read_cluster.py
SemiBin/main.py
SemiBin/marker.hmm
SemiBin/markers.py
SemiBin/naive_orffinder.py
SemiBin/orffinding.py
SemiBin/self_supervised_model.py
SemiBin/semi_supervised_model.py
SemiBin/semibin_version.py
SemiBin/utils.py
SemiBin/models/built_environment_model.pt
SemiBin/models/cat_gut_model.pt
SemiBin/models/chicken_caecum_model.pt
SemiBin/models/dog_gut_model.pt
SemiBin/models/global_model.pt
SemiBin/models/human_gut_model.pt
SemiBin/models/human_oral_model.pt
SemiBin/models/mouse_gut_model.pt
SemiBin/models/ocean_model.pt
SemiBin/models/pig_gut_model.pt
SemiBin/models/soil_model.pt
SemiBin/models/wastewater_model.pt
semibin-2.2.1.dist-info/METADATA
semibin-2.2.1.dist-info/WHEEL
semibin-2.2.1.dist-info/entry_points.txt
semibin-2.2.1.dist-info/top_level.txt
semibin-2.2.1.dist-info/RECORD
