Metadata-Version: 2.4
Name: SemiBin
Version: 2.2.1
Summary: Metagenomic binning with siamese neural networks
Author: Shaojun Pan
Author-email: Luis Pedro Coelho <luis@luispedro.org>
License: MIT
Project-URL: homepage, https://github.com/BigDataBiology/SemiBin
Classifier: Development Status :: 5 - Production/Stable
Classifier: Intended Audience :: Science/Research
Classifier: Topic :: Scientific/Engineering :: Bio-Informatics
Classifier: Topic :: Scientific/Engineering :: Artificial Intelligence
Classifier: License :: OSI Approved :: MIT License
Classifier: Programming Language :: Python :: 3.8
Classifier: Programming Language :: Python :: 3.9
Classifier: Programming Language :: Python :: 3.10
Classifier: Programming Language :: Python :: 3.11
Classifier: Programming Language :: Python :: 3.12
Classifier: Programming Language :: Python :: 3.13
Requires-Python: >=3.8
Requires-Dist: numpy
Requires-Dist: tqdm
Requires-Dist: pyyaml
Requires-Dist: torch>=1.13
Requires-Dist: python-igraph
Requires-Dist: pandas
Requires-Dist: scikit-learn
Requires-Dist: requests
Requires-Dist: numexpr
Provides-Extra: dev
Requires-Dist: pytest; extra == "dev"
Requires-Dist: hypothesis<=6.112.1; extra == "dev"
